{
  "task_id": "47c9b24b-a043-4542-9025-a4ddfa1b4df9",
  "task_type": "single",
  "status": "completed",
  "created_at": "2026-01-04T18:51:19.302779",
  "started_at": "2026-01-04T18:51:19.305784",
  "completed_at": "2026-01-04T18:51:34.867130",
  "progress": 100,
  "message": "Review completed successfully",
  "error": null,
  "result_data": {
    "envw_path": "C:\\Users\\CSonneveld\\OneDrive - Euronext\\Documents\\Projects\\GUI + Reviews\\output\\ENVW_df_20260104_185133.xlsx"
  },
  "review_type": "ENVW",
  "parameters": {
    "date": "20250709",
    "co_date": "20250704",
    "effective_date": "11-Jul-25",
    "index": "ENVW",
    "isin": "QS0011250840",
    "auto_open": true,
    "is_local_request": true
  },
  "duration_seconds": 15.559347
}