{
  "task_id": "5b509cf3-216e-4e01-a253-2e77324ebaa7",
  "task_type": "batch",
  "status": "failed",
  "created_at": "2025-09-15T19:07:45.333761",
  "started_at": "2025-09-15T19:07:45.334762",
  "completed_at": "2025-09-15T19:07:55.356765",
  "progress": 0,
  "message": "Task interrupted by server restart",
  "error": "Server restarted during task execution",
  "result_data": null,
  "review_type": null,
  "parameters": {
    "review_types": [
      "AEXEW",
      "BE1P",
      "BNEW",
      "CACEW",
      "CLEW",
      "DAREP",
      "DEREP",
      "DWREP",
      "EDEFP",
      "EDWP",
      "EDWPT",
      "EEFAP",
      "EES2",
      "EESF",
      "EFMEP",
      "EGSPP",
      "ELECP",
      "ELTFP",
      "ELUXP",
      "ERI5P",
      "ESVEP",
      "ETPFB",
      "ETSEP",
      "EUADP",
      "EUREP",
      "EUS5P",
      "EZ15P",
      "EZ40P",
      "EZ60P",
      "EZN1P",
      "F4RIP",
      "FR20P",
      "FRECP",
      "FRI4P",
      "FRN4P",
      "GICP",
      "GSFBP",
      "SECTORIAL",
      "WIFRP"
    ],
    "date": "20250912",
    "co_date": "20250822",
    "effective_date": "22-Sep-25",
    "currency": "EUR",
    "auto_open": false,
    "is_local_request": true
  },
  "duration_seconds": null
}