{
  "task_id": "13f8a0e4-5d3a-44e9-adbe-3fbed8727254",
  "task_type": "single",
  "status": "completed",
  "created_at": "2025-12-16T12:41:52.740926",
  "started_at": "2025-12-16T12:41:52.740926",
  "completed_at": "2025-12-16T12:41:54.607410",
  "progress": 100,
  "message": "Review completed successfully",
  "error": null,
  "result_data": {
    "bnew_path": "C:\\Users\\CSonneveld\\OneDrive - Euronext\\Documents\\Projects\\GUI + Reviews\\output\\BNEW_df_20251216_124154.xlsx"
  },
  "review_type": "BNEW",
  "parameters": {
    "date": "20251211",
    "co_date": "20251121",
    "effective_date": "22-Dec-25",
    "index": "BNEW",
    "isin": "NL0011376116",
    "currency": "EUR",
    "auto_open": true,
    "is_local_request": true
  },
  "duration_seconds": 1.850521
}