{
  "task_id": "f16188ad-4aca-48fd-abd2-201d65eb9be0",
  "task_type": "single",
  "status": "completed",
  "created_at": "2025-12-05T11:22:15.948252",
  "started_at": "2025-12-05T11:22:15.951251",
  "completed_at": "2025-12-05T11:22:27.735641",
  "progress": 100,
  "message": "Review completed successfully",
  "error": null,
  "result_data": {
    "ezcla_path": "C:\\Users\\CSonneveld\\OneDrive - Euronext\\Documents\\Projects\\GUI + Reviews\\output\\EZCLA_df_20251205_112227.xlsx"
  },
  "review_type": "EZCLA",
  "parameters": {
    "date": "20250916",
    "co_date": "20250822",
    "effective_date": "22-Sep-25",
    "index": "EZCLA",
    "isin": "FR0014005IK5",
    "currency": "EUR",
    "auto_open": true,
    "is_local_request": true
  },
  "duration_seconds": 11.782387
}